pypi_test_coltg5/__init__.py
yeahyeah/__init__.py
yeahyeah/gang_slime.py
pypi_test_coltg5-0.2.4.dist-info/METADATA
pypi_test_coltg5-0.2.4.dist-info/WHEEL
pypi_test_coltg5-0.2.4.dist-info/RECORD
