Metadata-Version: 2.4
Name: pypi-test-coltg5
Version: 0.2.4
Summary: testing building and publishing a uv project w hatchling to pypi
Requires-Python: >=3.12
Requires-Dist: numpy>=2.3.2
